Metadata-Version: 2.1
Name: odoo10-addon-mail-check-mailbox-size
Version: 10.0.1.0.0.99.dev6
Summary: Send an email summarizing the current space used by a mailbox
Home-page: https://github.com/OCA/social
Author: Agile Business Group, Odoo Community Association (OCA)
Author-email: support@odoo-community.org
License: LGPL-3
Platform: UNKNOWN
Classifier: Programming Language :: Python
Classifier: Framework :: Odoo
Classifier: Framework :: Odoo :: 10.0
Classifier: License :: OSI Approved :: GNU Lesser General Public License v3 (LGPLv3)
Classifier: Development Status :: 4 - Beta
Requires-Python: ~=2.7
Requires-Dist: odoo <10.1dev,>=10.0
